server_admin-0.1.0.data/scripts/fetch-backup
server_admin-0.1.0.data/scripts/gitlab-backup
server_admin-0.1.0.data/scripts/gitlab-repo-backup
server_admin-0.1.0.dist-info/DESCRIPTION.rst
server_admin-0.1.0.dist-info/METADATA
server_admin-0.1.0.dist-info/RECORD
server_admin-0.1.0.dist-info/WHEEL
server_admin-0.1.0.dist-info/metadata.json
server_admin-0.1.0.dist-info/top_level.txt
server_admintools/__init__.py
server_admintools/__init__.py.bak
server_admintools/gitlab.py
server_admintools/gitlab.py.bak
server_admintools/rsync.py
server_admintools/rsync.py.bak
server_admintools/sudo.py
server_admintools/sudo.py.bak
