Metadata-Version: 2.0
Name: server-admin
Version: 0.1.0
Summary: A collection of server administration bin
Home-page: https://gitlab.namibsun.net/namboy94/server-admin
Author: Hermann Krumrey
Author-email: hermann@krumreyh.com
License: GNU GPL3
Download-URL: https://gitlab.namibsun.net/namboy94/server-admin/repository/archive.zip?ref=master
Platform: UNKNOWN
Classifier: Environment :: Console
Classifier: Natural Language :: English
Classifier: Intended Audience :: System Administrators
Classifier: Development Status :: 1 - Planning
Classifier: Operating System :: POSIX :: Linux
Classifier: Programming Language :: Python
Classifier: Topic :: System :: Systems Administration
Classifier: License :: OSI Approved :: GNU General Public License v3 (GPLv3)
